pyzid/__about__.py
pyzid/__init__.py
pyzid/_encoding.py
pyzid/_id.py
pyzid/_node.py
pyzid/_utils.py
pyzid-0.0.2.dist-info/METADATA
pyzid-0.0.2.dist-info/WHEEL
pyzid-0.0.2.dist-info/licenses/LICENSE
pyzid-0.0.2.dist-info/RECORD
