Metadata-Version: 2.4
Name: pyzid
Version: 0.0.2
Summary: A sortable unique identifier generator.
Project-URL: Homepage, https://github.com/deadblue/pyzid
Project-URL: Repository, https://github.com/deadblue/pyzid
Author-email: deadblue <root@dead.blue>
License-Expression: MIT
License-File: LICENSE
Classifier: Development Status :: 4 - Beta
Classifier: License :: OSI Approved :: MIT License
Classifier: Operating System :: OS Independent
Classifier: Programming Language :: Python
Classifier: Programming Language :: Python :: 3
Requires-Python: >=3.11
